command/__init__.py
command/suite.py
common/__init__.py
common/config.py
common/filesystem.py
stf/__init__.py
stf/cli.py
stf/assets/config.base.yml
stf/assets/docker-compose.base.yml
stf/command/__init__.py
stf/command/config.py
stf/command/grid.py
stf/command/suite.py
stf/common/__init__.py
stf/common/config.py
stf/common/docker.py
stf/common/filesystem.py
stf/test/__init__.py
stf/test/test_common_config.py
stf/test_case/__init__.py
stf/test_case/base.py
stf/test_case/magento.py
stf/test_case/sample/__init__.py
stf/test_case/sample/magento.py
stf/test_case/sample/simple.py
test_case/__init__.py
test_case/base.py
test_case/magento.py
tests/__init__.py
tests/test_common_config.py
summa_testing_framework_summasolutions-0.1.16.dist-info/LICENSE
summa_testing_framework_summasolutions-0.1.16.dist-info/METADATA
summa_testing_framework_summasolutions-0.1.16.dist-info/WHEEL
summa_testing_framework_summasolutions-0.1.16.dist-info/entry_points.txt
summa_testing_framework_summasolutions-0.1.16.dist-info/top_level.txt
summa_testing_framework_summasolutions-0.1.16.dist-info/RECORD
